lxmfy_translate_bot/__init__.py
lxmfy_translate_bot/bot.py
lxmfy_translate_bot-1.2.2.dist-info/METADATA
lxmfy_translate_bot-1.2.2.dist-info/WHEEL
lxmfy_translate_bot-1.2.2.dist-info/entry_points.txt
lxmfy_translate_bot-1.2.2.dist-info/licenses/LICENSE
lxmfy_translate_bot-1.2.2.dist-info/RECORD
