Metadata-Version: 2.4
Name: lxmfy-translate-bot
Version: 1.2.2
Summary: translate-bot for lxmf
License-File: LICENSE
Author: Ivan
Requires-Python: >=3.11,<3.14
Classifier: Programming Language :: Python :: 3
Classifier: Programming Language :: Python :: 3.11
Classifier: Programming Language :: Python :: 3.12
Classifier: Programming Language :: Python :: 3.13
Provides-Extra: dev
Requires-Dist: argostranslate (>=1.9.6,<2.0.0)
Requires-Dist: build ; extra == "dev"
Requires-Dist: lxmfy (>=1.0.3,<2.0.0)
Requires-Dist: srsly (>=2.5.1,<3.0.0)
Requires-Dist: twine ; extra == "dev"
